[
  {
    "ticker": "AAPL",
    "recommendation": "Hold",
    "reasoning": "For a cautious long-term growth investor, Apple presents a mixed picture. The LSTM model forecasts a price slightly below the actual price, while the MLP model predicts a higher price. Given the conflicting signals and the investor's risk aversion, a 'Hold' recommendation is prudent. Monitor future performance and model revisions.",
    "forecast": {
      "LSTM": {
        "target_date": "2025-01-02",
        "actual_price": 243.8500061035156,
        "predicted_price": 240.80037829293377,
        "performance": "Slightly Underperforming"
      },
      "MLP": {
        "target_date": "2025-01-02",
        "actual_price": 243.8500061035156,
        "predicted_price": 259.0205064363517,
        "performance": "Outperforming"
      }
    }
  },
  {
    "ticker": "AMD",
    "recommendation": "Hold",
    "reasoning": "AMD's forecast results are also mixed. The LSTM model predicts a higher price, but the MLP model is very close to the actual price, suggesting stability. Considering the cautious investor profile, a 'Hold' recommendation is advised. Continue to monitor AMD's performance and sector trends.",
    "forecast": {
      "LSTM": {
        "target_date": "2025-01-02",
        "actual_price": 120.62999725341795,
        "predicted_price": 128.27006019707784,
        "performance": "Outperforming"
      },
      "MLP": {
        "target_date": "2025-01-02",
        "actual_price": 120.62999725341795,
        "predicted_price": 120.98455383379223,
        "performance": "Neutral"
      }
    }
  },
  {
    "ticker": "GOOGL",
    "recommendation": "Buy",
    "reasoning": "Both LSTM and MLP models forecast a price increase for GOOGL. Given this consensus and the long-term growth focus, a 'Buy' recommendation is warranted. However, the investor should proceed cautiously and monitor market conditions.",
    "forecast": {
      "LSTM": {
        "target_date": "2025-01-02",
        "actual_price": 189.42999267578125,
        "predicted_price": 191.39196004342895,
        "performance": "Outperforming"
      },
      "MLP": {
        "target_date": "2025-01-02",
        "actual_price": 189.42999267578125,
        "predicted_price": 195.23705711169396,
        "performance": "Outperforming"
      }
    }
  }
]